pangres/__init__.py
pangres/_version.py
pangres/core.py
pangres/engine.py
pangres/examples.py
pangres/exceptions.py
pangres/executor.py
pangres/helpers.py
pangres/logger.py
pangres/pangres_types.py
pangres/py.typed
pangres/transaction.py
pangres/upsert_query.py
pangres/utils.py
pangres/tests/__init__.py
pangres/tests/conftest.py
pangres/tests/test_bad_text.py
pangres/tests/test_chunksize.py
pangres/tests/test_con_and_trans_control.py
pangres/tests/test_core.py
pangres/tests/test_helpers.py
pangres/tests/test_index.py
pangres/tests/test_logging.py
pangres/tests/test_pandas_special_engine.py
pangres/tests/test_unique_key.py
pangres/tests/test_upsert_speed.py
pangres/tests/test_utils.py
pangres/tests/test_yield_chunks.py
pangres-4.1.4.dist-info/LICENSE
pangres-4.1.4.dist-info/METADATA
pangres-4.1.4.dist-info/WHEEL
pangres-4.1.4.dist-info/top_level.txt
pangres-4.1.4.dist-info/RECORD
