Metadata-Version: 2.1
Name: pangres
Version: 4.1.4
Summary: Postgres insert update with pandas DataFrames.
Home-page: https://github.com/ThibTrip/pangres
Download-URL: https://github.com/ThibTrip/pangres/archive/v4.1.4.tar.gz
Author: Thibault Bétrémieux
Author-email: thibault.betremieux@gmail.com
License: The Unlicense
Keywords: pandas,postgres,mysql,sqlite
Classifier: Development Status :: 5 - Production/Stable
Classifier: Programming Language :: Python :: 3
Classifier: Programming Language :: Python :: 3.6
Classifier: Programming Language :: Python :: 3.7
Classifier: Programming Language :: Python :: 3.8
Classifier: Programming Language :: Python :: 3.9
Classifier: Programming Language :: Python :: 3.10
Classifier: Programming Language :: Python :: 3.11
Classifier: License :: Public Domain
Classifier: Intended Audience :: Developers
Classifier: Operating System :: OS Independent
License-File: LICENSE
Requires-Dist: pandas (>=0.25.3)
Requires-Dist: sqlalchemy (>=1.3.12)
Requires-Dist: alembic (>=1.3.1)
